{"nodes": [{"id": "rart_wprrt_saved_requests", "label": "WPRRT_Saved_Requests", "file_type": "code", "source_file": "includes/class-saved-requests.php", "source_location": "8:52", "source_url": null, "captured_at": null, "author": null, "contributor": null}, {"id": "rart_usermeta_saved_requests", "label": "Per-User Saved Requests in wp_usermeta", "file_type": "rationale", "source_file": "includes/class-saved-requests.php", "source_location": "4:11", "source_url": null, "captured_at": null, "author": null, "contributor": null}, {"id": "saved_requests_feature", "label": "Saved requests persistence", "file_type": "rationale", "source_file": "includes/class-saved-requests.php", "source_location": null, "source_url": null, "captured_at": null, "author": null, "contributor": null}], "edges": [{"source": "rart_wprrt_saved_requests", "target": "rart_usermeta_saved_requests", "relation": "rationale_for", "confidence": "EXTRACTED", "confidence_score": 1.0, "source_file": "includes/class-saved-requests.php", "source_location": "4:11", "weight": 1.0}, {"source": "rest_api_route_tester_plugin", "target": "saved_requests_feature", "relation": "conceptually_related_to", "confidence": "INFERRED", "confidence_score": 0.75, "source_file": "includes/class-saved-requests.php", "source_location": null, "weight": 1.0}], "hyperedges": [{"id": "rart_saved_requests_crud", "label": "Saved Requests CRUD Pipeline", "nodes": ["rart_wprrt_saved_requests", "rart_method_save_request", "rart_method_get_saved_requests", "rart_method_delete_request", "rart_fn_save_current_tab", "rart_usermeta_saved_requests"], "relation": "implement", "confidence": "EXTRACTED", "confidence_score": 1.0, "source_file": "includes/class-saved-requests.php"}]}